netplotlib/VERSION.txt
netplotlib/__init__.py
netplotlib/layout.py
netplotlib/netplotlib.py
netplotlib/testmodels.py
netplotlib/toolbox.py
netplotlib/testcases/test_AspartateMetabolism.xml
netplotlib/testcases/test_BIOMD0000000010.xml
netplotlib/testcases/test_BIOMD0000000012.xml
netplotlib/testcases/test_BIOMD0000000019.xml
netplotlib/testcases/test_BIOMD0000000223.xml
netplotlib/testcases/test_autoreg_act.xml
netplotlib/testcases/test_autoreg_act_conn.xml
netplotlib/testcases/test_autoreg_inb.xml
netplotlib/testcases/test_autoreg_inb_conn.xml
netplotlib/testcases/test_bibi.xml
netplotlib/testcases/test_bibireversible.xml
netplotlib/testcases/test_biuni.xml
netplotlib/testcases/test_biunireversible.xml
netplotlib/testcases/test_branched.xml
netplotlib/testcases/test_conservedcycle.xml
netplotlib/testcases/test_feedback.xml
netplotlib/testcases/test_galactose.xml
netplotlib/testcases/test_glycolysis.xml
netplotlib/testcases/test_layout1.xml
netplotlib/testcases/test_layout2.xml
netplotlib/testcases/test_list11.xml
netplotlib/testcases/test_list12.xml
netplotlib/testcases/test_list13.xml
netplotlib/testcases/test_list21.xml
netplotlib/testcases/test_list22.xml
netplotlib/testcases/test_list23.xml
netplotlib/testcases/test_no_kl.xml
netplotlib/testcases/test_no_kl_reversible.xml
netplotlib/testcases/test_reversible.xml
netplotlib/testcases/test_stoch1.xml
netplotlib/testcases/test_stoch2.xml
netplotlib/testcases/test_stoch3.xml
netplotlib/testcases/test_sympy.xml
netplotlib/testcases/test_twocycles.xml
netplotlib/testcases/test_undefBoundary.xml
netplotlib/testcases/test_unibi.xml
netplotlib/testcases/test_unibireversible.xml
netplotlib/testcases/test_uniunireversible.xml
netplotlib-1.2.2.dist-info/LICENSE
netplotlib-1.2.2.dist-info/METADATA
netplotlib-1.2.2.dist-info/WHEEL
netplotlib-1.2.2.dist-info/top_level.txt
netplotlib-1.2.2.dist-info/RECORD
